{
  "title": "조달청, 본청·지방청 계약담당자 120명과 간담회｜공공조달 혁신 논의",
  "author": "조달청소식",
  "date": "2025/09/19 09:57",
  "url": "http://blog.naver.com/kangsan2023/224008389734",
  "body": "조달청, 구매업무 계약담당자 소통 간담회 개최조달청, 구매업무 계약담당자 소통 간담회 개최\n- 본청·지방청 구매업무 계약담당자 약 120명 대상 애로사항 청취- 본청·지방청 구매업무 계약담당자 약 120명 대상 애로사항 청취\n- 조달단가계약 의무구매 자율화, 조달기업 편의 제고 방안 등 토론- 조달단가계약 의무구매 자율화, 조달기업 편의 제고 방안 등 토론\n조달청(청장 백승보)은 정부대전청사에서 구매계약업무 담당 120여 명의 직원이 참여한 가운데 “구매업무 계약담당자 대\n상 소통 간담회”를 개최했다.\n이번 간담회는 지난 9일 조달청장 주재 타운홀 미팅에서 조달정책 분야 건의사항의 대부분이 구매계약업무 관련이었던 점\n을 고려하여 개최되었다.\n간담회에서는 △공공조달 개혁방안의 핵심내용인 조달단가계약 의무구매 자율화 방안, △조달기업 편의 제고 방안, △다\n수공급자계약 차기공고 정비 방안 등에 대하여 직원들 간에 내용을 공유하고 자유롭게 토론하는 시간이 이어졌다.\n강성민 구매사업국장은 “본청·지방청 직원들이 허심탄회하게 의견을 주고 받는 의미있는 자리였다”면서, “현장의 의견을\n적극 반영하여 계약담당자들이 보람있게 일할 수 있도록 업무방식 개선 등에 최선을 다하겠다“고 밝혔다.\n* 문의: 구매총괄과 정화연 사무관(042-724-7265)"
}